README.md
setup.py
MT_PY_NotificationPush/__init__.py
MT_PY_NotificationPush/main.py
MT_PY_NotificationPush.egg-info/PKG-INFO
MT_PY_NotificationPush.egg-info/SOURCES.txt
MT_PY_NotificationPush.egg-info/dependency_links.txt
MT_PY_NotificationPush.egg-info/top_level.txt