Metadata-Version: 2.1
Name: MT-PY-NotificationPush
Version: 1.0.0
Summary: Notification Push
Author: Pradnya Kakade
Author-email: pradnyak.in@mouritech.com
